doopass_libs/__init__.py
doopass_libs/core/__init__.py
doopass_libs/core/components/backup_manage_menu.py
doopass_libs/core/components/login_page.py
doopass_libs/core/components/login_page_container.py
doopass_libs/core/components/message.py
doopass_libs/core/components/select_menu.py
doopass_libs/core/components/signup_page.py
doopass_libs/core/components/store_handle_menu.py
doopass_libs/core/components/store_handle_menu_item.py
doopass_libs/core/components/store_pair_handle_page.py
doopass_libs/core/constants.py
doopass_libs/core/exceptions.py
doopass_libs/core/password_validation.py
doopass_libs/core/screens/__init__.py
doopass_libs/core/screens/backup_manage_screen.py
doopass_libs/core/screens/help_screen.py
doopass_libs/core/screens/login_screen.py
doopass_libs/core/screens/main_menu_screen.py
doopass_libs/core/screens/main_screen.py
doopass_libs/core/screens/message_screen.py
doopass_libs/core/screens/screen.py
doopass_libs/core/screens/sign_up_screen.py
doopass_libs/core/screens/store_handle_screen.py
doopass_libs/core/screens/store_pair_handle_screen.py
doopass_libs/core/store.py
doopass_libs/core/store_backup.py
doopass_libs-1.0.7.dist-info/LICENSE
doopass_libs-1.0.7.dist-info/METADATA
doopass_libs-1.0.7.dist-info/WHEEL
doopass_libs-1.0.7.dist-info/RECORD
